{"ref":"22eddd9d-3fbd-4ff2-addd-edc7f6e0574b","syncData":{"version":2,"machineId":"75bfb870-4ab3-433f-bc3f-95a126a848f6","content":"{\"settings\":\"{\\r\\n    // \\\"code-runner.terminalRoot\\\": \\\"/\\\",\\r\\n    \\\"[dart]\\\": {\\r\\n        \\\"editor.formatOnSave\\\": true\\r\\n    },\\r\\n    \\\"editor.mouseWheelZoom\\\": false,\\r\\n    \\\"code-runner.runInTerminal\\\": true,\\r\\n    \\\"extensions.ignoreRecommendations\\\": true,\\r\\n    \\\"window.openFilesInNewWindow\\\": \\\"on\\\",\\r\\n    \\\"editor.bracketPairColorization.enabled\\\": true,\\r\\n    \\\"editor.guides.bracketPairs\\\": true,\\r\\n    \\\"editor.formatOnSave\\\": true,\\r\\n    \\\"editor.fontLigatures\\\": true,\\r\\n    \\\"editor.minimap.enabled\\\": false,\\r\\n    \\\"editor.fontFamily\\\": \\\"'JetBrainsMono Nerd Font','Iosevka Nerd Font','monospace'\\\",\\r\\n    \\\"editor.suggestSelection\\\": \\\"first\\\",\\r\\n    \\\"vsintellicode.modify.editor.suggestSelection\\\": \\\"automaticallyOverrodeDefaultValue\\\",\\r\\n    \\\"files.exclude\\\": {\\r\\n        \\\"**/.classpath\\\": true,\\r\\n        \\\"**/.factorypath\\\": true,\\r\\n        \\\"**/.git\\\": false,\\r\\n        \\\"**/.project\\\": true,\\r\\n        \\\"**/.settings\\\": true\\r\\n    },\\r\\n    \\\"[jsonc]\\\": {\\r\\n        \\\"editor.defaultFormatter\\\": \\\"vscode.json-language-features\\\"\\r\\n    },\\r\\n    \\\"cph.general.defaultLanguage\\\": \\\"cpp\\\",\\r\\n    \\\"cph.general.retainWebviewContext\\\": true,\\r\\n    // \\\"workbench.experimental.layoutControl.enabled\\\": true,\\r\\n    \\\"explorer.confirmDelete\\\": false,\\r\\n    \\\"[cpp]\\\": {\\r\\n        \\\"editor.defaultFormatter\\\": \\\"llvm-vs-code-extensions.vscode-clangd\\\"\\r\\n    },\\r\\n    \\\"codesnap.shutterAction\\\": \\\"copy\\\",\\r\\n    \\\"leetcode.endpoint\\\": \\\"leetcode\\\",\\r\\n    \\\"codesnap.showWindowControls\\\": false,\\r\\n    \\\"codesnap.transparentBackground\\\": true,\\r\\n    \\\"editor.smoothScrolling\\\": true,\\r\\n    \\\"workbench.list.smoothScrolling\\\": true,\\r\\n    \\\"vsicons.dontShowNewVersionMessage\\\": true,\\r\\n    \\\"window.commandCenter\\\": true,\\r\\n    \\\"[java]\\\": {\\r\\n        \\\"editor.defaultFormatter\\\": \\\"redhat.java\\\"\\r\\n    },\\r\\n    // \\\"javascript.format.placeOpenBraceOnNewLineForControlBlocks\\\": true,\\r\\n    // \\\"javascript.format.placeOpenBraceOnNewLineForFunctions\\\": true,\\r\\n    // \\\"typescript.format.placeOpenBraceOnNewLineForControlBlocks\\\": true,\\r\\n    // \\\"typescript.format.placeOpenBraceOnNewLineForFunctions\\\": true,\\r\\n    \\\"editor.detectIndentation\\\": false,\\r\\n    \\\"terminal.integrated.defaultProfile.windows\\\": \\\"Command Prompt\\\",\\r\\n    \\\"oneDarkPro.italic\\\": false,\\r\\n    \\\"oneDarkPro.vivid\\\": true,\\r\\n    \\\"terminal.integrated.profiles.windows\\\": {\\r\\n        \\\"PowerShell\\\": {\\r\\n            \\\"source\\\": \\\"PowerShell\\\",\\r\\n            \\\"icon\\\": \\\"terminal-powershell\\\"\\r\\n        },\\r\\n        \\\"Command Prompt\\\": {\\r\\n            \\\"path\\\": [\\r\\n                \\\"${env:windir}\\\\\\\\Sysnative\\\\\\\\cmd.exe\\\",\\r\\n                \\\"${env:windir}\\\\\\\\System32\\\\\\\\cmd.exe\\\"\\r\\n            ],\\r\\n            \\\"args\\\": [],\\r\\n            \\\"icon\\\": \\\"terminal-cmd\\\"\\r\\n        },\\r\\n        \\\"Git Bash\\\": {\\r\\n            \\\"source\\\": \\\"Git Bash\\\"\\r\\n        },\\r\\n        \\\"Windows PowerShell\\\": {\\r\\n            \\\"path\\\": \\\"C:\\\\\\\\WINDOWS\\\\\\\\System32\\\\\\\\WindowsPowerShell\\\\\\\\v1.0\\\\\\\\powershell.exe\\\"\\r\\n        }\\r\\n    },\\r\\n    \\\"dart.previewFlutterUiGuides\\\": true,\\r\\n    \\\"dart.previewFlutterUiGuidesCustomTracking\\\": true,\\r\\n    \\\"editor.stickyScroll.enabled\\\": true,\\r\\n    \\\"terminal.integrated.smoothScrolling\\\": true,\\r\\n    \\\"notebook.output.textLineLimit\\\": 50,\\r\\n    \\\"background.editor\\\": {\\r\\n        \\\"images\\\": [\\r\\n            \\\"https://user-images.githubusercontent.com/9987486/40583669-d6189844-61c5-11e8-89e3-c52ad153da09.png\\\",\\r\\n            \\\"https://user-images.githubusercontent.com/9987486/40583670-d6478c9e-61c5-11e8-9551-6b55eacc7b8d.png\\\",\\r\\n            \\\"https://user-images.githubusercontent.com/9987486/40583671-d676c6e4-61c5-11e8-94cb-34ec4a12fa01.png\\\"\\r\\n        ],\\r\\n        \\\"style\\\": {\\r\\n            \\\"content\\\": \\\"''\\\",\\r\\n            \\\"pointer-events\\\": \\\"none\\\",\\r\\n            \\\"position\\\": \\\"absolute\\\",\\r\\n            \\\"z-index\\\": \\\"99999\\\",\\r\\n            \\\"width\\\": \\\"100%\\\",\\r\\n            \\\"height\\\": \\\"100%\\\",\\r\\n            \\\"background-size\\\": \\\"100px\\\",\\r\\n            \\\"background-position\\\": \\\"100% 100%\\\",\\r\\n            \\\"background-repeat\\\": \\\"no-repeat\\\",\\r\\n            \\\"opacity\\\": 0.3\\r\\n        },\\r\\n        \\\"fullscreen\\\": {\\r\\n            \\\"image\\\": \\\"\\\",\\r\\n            \\\"opacity\\\": 0.91,\\r\\n            \\\"size\\\": \\\"cover\\\",\\r\\n            \\\"interval\\\": 0\\r\\n        }\\r\\n    },\\r\\n    \\\"background.loop\\\": true,\\r\\n    \\\"warmUp.changeCount\\\": \\\"15\\\",\\r\\n    \\\"warmUp.switchProgrammingLanguage\\\": \\\"cpp\\\",\\r\\n    \\\"editor.accessibilitySupport\\\": \\\"off\\\",\\r\\n    \\\"svelte.enable-ts-plugin\\\": true,\\r\\n    \\\"svelte.plugin.svelte.note-new-transformation\\\": false,\\r\\n    \\\"css.lint.unknownAtRules\\\": \\\"ignore\\\",\\r\\n    \\\"jupyter.widgetScriptSources\\\": [\\r\\n        \\\"jsdelivr.com\\\",\\r\\n        \\\"unpkg.com\\\"\\r\\n    ],\\r\\n    \\\"[python]\\\": {\\r\\n        \\\"editor.formatOnType\\\": true,\\r\\n        \\\"editor.defaultFormatter\\\": \\\"ms-python.black-formatter\\\"\\r\\n    },\\r\\n    \\\"emmet.includeLanguages\\\": {\\r\\n        \\\"django-html\\\": \\\"html\\\"\\r\\n    },\\r\\n    \\\"files.associations\\\": {\\r\\n        \\\"*.html\\\": \\\"html\\\",\\r\\n        \\\"*.svg\\\": \\\"image\\\"\\r\\n    },\\r\\n    //vim settings\\r\\n    \\\"vim.useCtrlKeys\\\": false,\\r\\n    \\\"vim.handleKeys\\\": {\\r\\n        \\\"<C-a>\\\": false,\\r\\n        \\\"<C-f>\\\": false,\\r\\n        \\\"<C-d>\\\": false,\\r\\n        \\\"<C-l>\\\": false,\\r\\n        \\\"<C-r>\\\": false\\r\\n    },\\r\\n    \\\"vim.insertModeKeyBindings\\\": [\\r\\n        {\\r\\n            \\\"before\\\": [\\r\\n                \\\"q\\\",\\r\\n                \\\"q\\\"\\r\\n            ],\\r\\n            \\\"after\\\": [\\r\\n                \\\"<Esc>\\\"\\r\\n            ]\\r\\n        }\\r\\n    ],\\r\\n    \\\"[svelte]\\\": {\\r\\n        \\\"editor.defaultFormatter\\\": \\\"svelte.svelte-vscode\\\"\\r\\n    },\\r\\n    \\\"svelte.plugin.svelte.format.config.svelteBracketNewLine\\\": false,\\r\\n    \\\"[javascript]\\\": {\\r\\n        \\\"editor.defaultFormatter\\\": \\\"esbenp.prettier-vscode\\\"\\r\\n    },\\r\\n    \\\"[html]\\\": {\\r\\n        \\\"editor.defaultFormatter\\\": \\\"esbenp.prettier-vscode\\\"\\r\\n    },\\r\\n    \\\"[typescript]\\\": {\\r\\n        \\\"editor.defaultFormatter\\\": \\\"esbenp.prettier-vscode\\\"\\r\\n    },\\r\\n    \\\"redhat.telemetry.enabled\\\": true,\\r\\n    \\\"rsp-ui.enableStartServerOnActivation\\\": [\\r\\n        {\\r\\n            \\\"id\\\": \\\"redhat.vscode-community-server-connector\\\",\\r\\n            \\\"name\\\": \\\"Community Server Connector\\\",\\r\\n            \\\"startOnActivation\\\": true\\r\\n        }\\r\\n    ],\\r\\n    \\\"tailwindCSS.experimental.configFile\\\": null,\\r\\n    \\\"[php]\\\": {\\r\\n        \\\"editor.defaultFormatter\\\": \\\"kokororin.vscode-phpfmt\\\"\\r\\n    },\\r\\n    \\\"[json]\\\": {\\r\\n        \\\"editor.defaultFormatter\\\": \\\"vscode.json-language-features\\\"\\r\\n    },\\r\\n    \\\"[typescriptreact]\\\": {\\r\\n        \\\"editor.defaultFormatter\\\": \\\"esbenp.prettier-vscode\\\"\\r\\n    },\\r\\n    \\\"[javascriptreact]\\\": {\\r\\n        \\\"editor.defaultFormatter\\\": \\\"esbenp.prettier-vscode\\\"\\r\\n    },\\r\\n    \\\"typescript.updateImportsOnFileMove.enabled\\\": \\\"always\\\",\\r\\n    \\\"terminal.integrated.env.windows\\\": {},\\r\\n    \\\"editor.defaultFormatter\\\": \\\"esbenp.prettier-vscode\\\",\\r\\n    \\\"prettier.enableDebugLogs\\\": true,\\r\\n    \\\"javascript.updateImportsOnFileMove.enabled\\\": \\\"always\\\",\\r\\n    \\\"[prisma]\\\": {\\r\\n        \\\"editor.defaultFormatter\\\": \\\"Prisma.prisma\\\"\\r\\n    },\\r\\n    \\\"terminal.integrated.enableMultiLinePasteWarning\\\": false,\\r\\n    \\\"prettier.useEditorConfig\\\": false,\\r\\n    \\\"explorer.confirmPasteNative\\\": false,\\r\\n    \\\"prisma.showPrismaDataPlatformNotification\\\": false,\\r\\n    \\\"liveServer.settings.donotShowInfoMsg\\\": true,\\r\\n    \\\"[shellscript]\\\": {\\r\\n        \\\"editor.defaultFormatter\\\": \\\"shakram02.bash-beautify\\\"\\r\\n    },\\r\\n    \\\"[c]\\\": {\\r\\n        \\\"editor.defaultFormatter\\\": \\\"llvm-vs-code-extensions.vscode-clangd\\\"\\r\\n    },\\r\\n    \\\"supermaven.enable\\\": {\\r\\n        \\\"*\\\": true\\r\\n    },\\r\\n    \\\"remote.SSH.useExecServer\\\": false,\\r\\n    \\\"remote.SSH.remotePlatform\\\": {\\r\\n        \\\"mars.cse.iitb.ac.in\\\": \\\"linux\\\"\\r\\n    },\\r\\n    \\\"git.openRepositoryInParentFolders\\\": \\\"never\\\",\\r\\n    \\\"react-native-tools.showUserTips\\\": false,\\r\\n    \\\"livePreview.openPreviewTarget\\\": \\\"External Browser\\\",\\r\\n    \\\"emmet.triggerExpansionOnTab\\\": true,\\r\\n    \\\"background.enabled\\\": false,\\r\\n    \\\"supermaven.enableFixWithSupermaven\\\": true,\\r\\n    \\\"explorer.fileNesting.patterns\\\": {\\r\\n        \\\"*.ts\\\": \\\"${capture}.js\\\",\\r\\n        \\\"*.js\\\": \\\"${capture}.js.map, ${capture}.min.js, ${capture}.d.ts\\\",\\r\\n        \\\"*.jsx\\\": \\\"${capture}.js\\\",\\r\\n        \\\"*.tsx\\\": \\\"${capture}.ts\\\",\\r\\n        \\\"tsconfig.json\\\": \\\"tsconfig.*.json\\\",\\r\\n        \\\"package.json\\\": \\\"package-lock.json, yarn.lock, pnpm-lock.yaml, bun.lockb\\\",\\r\\n        \\\"*.sqlite\\\": \\\"${capture}.${extname}-*\\\",\\r\\n        \\\"*.db\\\": \\\"${capture}.${extname}-*\\\",\\r\\n        \\\"*.sqlite3\\\": \\\"${capture}.${extname}-*\\\",\\r\\n        \\\"*.db3\\\": \\\"${capture}.${extname}-*\\\",\\r\\n        \\\"*.sdb\\\": \\\"${capture}.${extname}-*\\\",\\r\\n        \\\"*.s3db\\\": \\\"${capture}.${extname}-*\\\"\\r\\n    },\\r\\n    \\\"codeforces-notify.handle\\\": \\\"sohampatel148e\\\",\\r\\n    \\\"window.titleBarStyle\\\": \\\"custom\\\",\\r\\n    \\\"explorer.confirmDragAndDrop\\\": false,\\r\\n    \\\"workbench.iconTheme\\\": \\\"material-icon-theme\\\",\\r\\n    \\\"editor.cursorSmoothCaretAnimation\\\": \\\"on\\\",\\r\\n    \\\"editor.cursorBlinking\\\": \\\"phase\\\",\\r\\n    \\\"terminal.integrated.gpuAcceleration\\\": \\\"off\\\",\\r\\n    \\\"[go]\\\": {\\r\\n        \\\"editor.defaultFormatter\\\": \\\"golang.go\\\"\\r\\n    },\\r\\n    \\\"excalidraw.theme\\\": \\\"light\\\",\\r\\n    \\\"svg.preview.boundingBox\\\": true,\\r\\n    \\\"svg.preview.autoOpen\\\": true,\\r\\n    \\\"workbench.editorAssociations\\\": {\\r\\n        \\\"*.svg\\\": \\\"svgPreviewer.customEditor\\\"\\r\\n    },\\r\\n    \\\"svg.preview.transparencyGrid\\\": false,\\r\\n    \\\"go.toolsManagement.autoUpdate\\\": true,\\r\\n    \\\"[solidity]\\\": {\\r\\n        \\\"editor.defaultFormatter\\\": \\\"JuanBlanco.solidity\\\"\\r\\n    },\\r\\n    \\\"tailwindCSS.includeLanguages\\\": {\\r\\n        \\\"html\\\": \\\"html\\\"\\r\\n    },\\r\\n    \\\"editor.quickSuggestions\\\": {\\r\\n        \\\"strings\\\": true\\r\\n    },\\r\\n    \\\"gitlens.views.scm.grouped.views\\\": {\\r\\n        \\\"commits\\\": true,\\r\\n        \\\"branches\\\": true,\\r\\n        \\\"remotes\\\": true,\\r\\n        \\\"stashes\\\": true,\\r\\n        \\\"tags\\\": true,\\r\\n        \\\"worktrees\\\": true,\\r\\n        \\\"contributors\\\": true,\\r\\n        \\\"fileHistory\\\": true,\\r\\n        \\\"repositories\\\": true,\\r\\n        \\\"searchAndCompare\\\": false,\\r\\n        \\\"launchpad\\\": false\\r\\n    },\\r\\n    \\\"workbench.sideBar.location\\\": \\\"right\\\",\\r\\n    \\\"github.copilot.enable\\\": {\\r\\n        \\\"*\\\": true,\\r\\n        \\\"plaintext\\\": true,\\r\\n        \\\"markdown\\\": false,\\r\\n        \\\"scminput\\\": false,\\r\\n        \\\"python\\\": false,\\r\\n        \\\"cpp\\\": false,\\r\\n        \\\"rust\\\": false\\r\\n    },\\r\\n    \\\"vim.useSystemClipboard\\\": true,\\r\\n    \\\"github.copilot.nextEditSuggestions.enabled\\\": false,\\r\\n    \\\"clangd.path\\\": \\\"/home/sohampatel/.config/Code/User/globalStorage/llvm-vs-code-extensions.vscode-clangd/install/20.1.8/clangd_20.1.8/bin/clangd\\\",\\r\\n    \\\"explorer.compactFolders\\\": false,\\r\\n    \\\"[proto3]\\\": {\\r\\n        \\\"editor.defaultFormatter\\\": \\\"zxh404.vscode-proto3\\\"\\r\\n    },\\r\\n    \\\"latex-workshop.docker.image.latex\\\": \\\"texlive/texlive\\\",\\r\\n    \\\"latex-workshop.formatting.latex\\\": \\\"tex-fmt\\\",\\r\\n    \\\"latex-workshop.docker.enabled\\\": true,\\r\\n    \\\"[latex]\\\": {\\r\\n        \\\"editor.defaultFormatter\\\": \\\"James-Yu.latex-workshop\\\"\\r\\n    },\\r\\n    \\\"latex-workshop.formatting.tex-fmt.path\\\": \\\"/home/sohampatel/.cargo/bin/tex-fmt\\\",\\r\\n    \\\"workbench.colorTheme\\\": \\\"GitHub Dark\\\",\\r\\n    \\\"jdk.telemetry.enabled\\\": false,\\r\\n    \\\"workbench.secondarySideBar.defaultVisibility\\\": \\\"hidden\\\",\\r\\n    \\\"terminal.integrated.allowedLinkSchemes\\\": [\\r\\n        \\\"file\\\",\\r\\n        \\\"http\\\",\\r\\n        \\\"https\\\",\\r\\n        \\\"mailto\\\",\\r\\n        \\\"vscode\\\",\\r\\n        \\\"vscode-insiders\\\",\\r\\n        \\\"apps/liveipo-app/src/navigation/TopNavigation.tsx\\\"\\r\\n    ],\\r\\n    \\\"terminal.integrated.suggest.enabled\\\": false,\\r\\n    \\\"chat.viewSessions.orientation\\\": \\\"stacked\\\",\\r\\n    \\\"editor.unicodeHighlight.invisibleCharacters\\\": false,\\r\\n    \\\"[astro]\\\": {\\r\\n        \\\"editor.defaultFormatter\\\": \\\"astro-build.astro-vscode\\\"\\r\\n    },\\r\\n    \\\"[lua]\\\": {\\r\\n        \\\"editor.defaultFormatter\\\": \\\"yinfei.luahelper\\\"\\r\\n    }\\r\\n    //end vim settings\\r\\n}\"}"}}